{
  "uid": "starter-peko",
  "status": "published",
  "name": "Peko",
  "description": "",
  "labels": [
    "starter",
    "framework"
  ],
  "display": {
    "avatar": "https://raw.githubusercontent.com/netzo/netzo/main/templates/starter-peko/icon.webp"
  },
  "links": [
    {
      "rel": "repository",
      "href": "https://github.com/netzo/netzo/tree/main/templates/starter-peko"
    },
    {
      "rel": "readme",
      "href": "https://raw.githubusercontent.com/netzo/netzo/main/templates/starter-peko/src/readme.md"
    }
  ],
  "item": {
    "_type": "project",
    "uid": "starter-peko",
    "fs": {
      "readme.md": {
        "url": "https://raw.githubusercontent.com/netzo/netzo/main/templates/starter-peko/src/readme.md"
      },
      "main.ts": {
        "url": "https://raw.githubusercontent.com/netzo/netzo/main/templates/starter-peko/src/main.ts"
      }
    },
    "configuration": {
      "entrypoint": "main.ts",
      "envVars": {},
      "permissions": {
        "net": true
      }
    }
  }
}
