{
  "uid": "resource-http-sendinblue",
  "type": "resource",
  "status": "published",
  "name": "Sendinblue",
  "description": "Resource for the Sendinblue API",
  "labels": [
    "marketing",
    "crm",
    "transactional"
  ],
  "display": {
    "imageUrl": "https://raw.githubusercontent.com/netzo/netzo/main/packages/resources/resource-http-sendinblue/icon.webp"
  },
  "links": [
    {
      "rel": "repository",
      "href": "https://github.com/netzo/netzo/tree/main/packages/resources/resource-http-sendinblue"
    },
    {
      "rel": "readme",
      "href": "https://raw.githubusercontent.com/netzo/netzo/main/packages/resources/resource-http-sendinblue/src/readme.md"
    }
  ],
  "item": {
    "_type": "resource",
    "type": "http",
    "base": {
      "baseURL": "https://api.sendinblue.com/v3",
      "headers": {
        "Content-Type": "application/json"
      },
      "authorization": {
        "type": "apiKey",
        "in": "header",
        "name": "api-key",
        "value": "{{apiKey}}"
      }
    }
  }
}