{
  "uid": "resource-http-sendinblue",
  "type": "resource",
  "status": "published",
  "name": "Sendinblue",
  "description": "Sendinblue is a transactional email service that allows you to send emails to your customers. It also provides a CRM to manage your contacts and a marketing automation tool to send automated emails to your contacts.",
  "labels": [
    "customer-service",
    "marketing",
    "sales",
    "chat",
    "communication/email"
  ],
  "display": {
    "avatar": "https://raw.githubusercontent.com/netzo/netzo/main/lib/apis/sendinblue/icon.webp"
  },
  "links": [
    {
      "rel": "repository",
      "href": "https://github.com/netzo/netzo/tree/main/lib/apis/sendinblue"
    },
    {
      "rel": "readme",
      "href": "https://raw.githubusercontent.com/netzo/netzo/main/lib/apis/sendinblue/src/readme.md"
    }
  ],
  "item": {
    "_type": "resource",
    "type": "http",
    "base": {
      "baseURL": "https://api.sendinblue.com/v3",
      "headers": {
        "Content-Type": "application/json"
      },
      "authorization": {
        "type": "apiKey",
        "in": "header",
        "name": "api-key",
        "value": "{{apiKey}}"
      }
    }
  }
}
